{
  "build": {
    "content": [
      { "dest": "entra-powershell", "files": [ "breadcrumb/toc.yml" ]},

      { "dest": "entra-powershell", "files": [ "**/*.md", "**/*.yml" ], "group": "conceptual", "src": "conceptual"},
	  
      { "dest": "module/entra-powershell", "files": [ "toc.yml" ], "group": "v1.0", "src": "reference/v1.0" },
      { "dest": "module", "files": [ "**/*.yml" ], "group": "v1.0", "src": "reference/v1.0" },
	  
      { "dest": "module/entra-powershell", "files": [ "toc.yml" ], "group": "beta", "src": "reference/beta" },
      { "dest": "module", "files": [ "**/*.yml" ], "group": "beta", "src": "reference/beta" },

      { "dest": "entra-powershell", "files": [ "**/*.md", "**/*.yml" ], "src": "virtual-folder" },
      { "dest": "module", "files": [ "**/*.md", "**/*.yml" ], "src": "virtual-folder-module" }
    ],
    "dest": "entra-powershell-reference",
    "groups": {
      "conceptual": { "moniker_range": "entra-powershell || entra-powershell-beta" },
      "v1.0": { "moniker_range": "entra-powershell" },
      "beta": { "moniker_range": "entra-powershell-beta" }
    },
    "overwrite": [],
    "externalReference": [],
    "globalMetadata": {
      "uhfHeaderId": "MSDocsHeader-Entra",
      "breadcrumb_path": "/powershell/entra-powershell/breadcrumb/toc.json",
      "extendBreadcrumb": true,
	  "ms.devlang": "powershell",
      "ms.prod": "powershell",
      "ms.topic": "reference",
      "feedback_system": "Standard",
	  "toc_preview": true
    },
    "template": [],
    "markdownEngineName": "markdig",
    "exportRawModel": true,
    "exportViewModel": true
  }
}
